actinia_openapi_python_client/__init__.py
actinia_openapi_python_client/api_client.py
actinia_openapi_python_client/api_response.py
actinia_openapi_python_client/configuration.py
actinia_openapi_python_client/exceptions.py
actinia_openapi_python_client/py.typed
actinia_openapi_python_client/rest.py
actinia_openapi_python_client/api/__init__.py
actinia_openapi_python_client/api/api_log_api.py
actinia_openapi_python_client/api/authentication_management_api.py
actinia_openapi_python_client/api/cache_management_api.py
actinia_openapi_python_client/api/file_management_api.py
actinia_openapi_python_client/api/geo_network_api.py
actinia_openapi_python_client/api/location_management_api.py
actinia_openapi_python_client/api/mapset_management_api.py
actinia_openapi_python_client/api/mapsets_api.py
actinia_openapi_python_client/api/merge_api.py
actinia_openapi_python_client/api/module_viewer_api.py
actinia_openapi_python_client/api/process_chain_monitoring_api.py
actinia_openapi_python_client/api/process_chain_template_management_api.py
actinia_openapi_python_client/api/processing_api.py
actinia_openapi_python_client/api/raster_management_api.py
actinia_openapi_python_client/api/raster_sampling_api.py
actinia_openapi_python_client/api/raster_statistics_api.py
actinia_openapi_python_client/api/resource_iteration_management_api.py
actinia_openapi_python_client/api/resource_management_api.py
actinia_openapi_python_client/api/satellite_image_algorithms_api.py
actinia_openapi_python_client/api/stac_api.py
actinia_openapi_python_client/api/strds_management_api.py
actinia_openapi_python_client/api/strds_sampling_api.py
actinia_openapi_python_client/api/strds_statistics_api.py
actinia_openapi_python_client/api/tiling_api.py
actinia_openapi_python_client/api/user_management_api.py
actinia_openapi_python_client/api/vector_management_api.py
actinia_openapi_python_client/api/vector_sampling_api.py
actinia_openapi_python_client/models/__init__.py
actinia_openapi_python_client-0.0.5.dist-info/LICENSE
actinia_openapi_python_client-0.0.5.dist-info/METADATA
actinia_openapi_python_client-0.0.5.dist-info/WHEEL
actinia_openapi_python_client-0.0.5.dist-info/top_level.txt
actinia_openapi_python_client-0.0.5.dist-info/RECORD
