Metadata-Version: 2.2
Name: actinia-openapi-python-client
Version: 0.0.5
Summary: Actinia OpenAPI Python Client
Home-page: https://github.com/OpenPlainsInc/actinia_openapi_python_client
Author: OpenPlainsInc
Author-email: developer@openplains.com
Keywords: OpenAPI,Actinia,OpenPlains,GRASS GIS
License-File: LICENSE
Requires-Dist: urllib3<=2.2.2,>=1.25.3
Requires-Dist: python-dateutil
Requires-Dist: pydantic>=2
Requires-Dist: typing-extensions>=4.7.1
Dynamic: author
Dynamic: author-email
Dynamic: description
Dynamic: description-content-type
Dynamic: home-page
Dynamic: keywords
Dynamic: requires-dist
Dynamic: summary
